dlblas/__init__.py
dlblas/cache.py
dlblas/op_registry.py
dlblas/op_struct.py
dlblas/symbolic_var.py
dlblas/autotune/__init__.py
dlblas/autotune/autotuner.py
dlblas/autotune/configs.py
dlblas/autotune/dynamic_compiler.py
dlblas/autotune/passes.py
dlblas/autotune/policy.py
dlblas/autotune/space.py
dlblas/frontend/__init__.py
dlblas/frontend/fx_parser.py
dlblas/frontend/fx_runnable_module_parser.py
dlblas/kernels/__init__.py
dlblas/kernels/activation.py
dlblas/kernels/add_rms_norm.py
dlblas/kernels/alibi_pagedattention.py
dlblas/kernels/allgather_grpo_loss.py
dlblas/kernels/apply_rotary_pos_emb.py
dlblas/kernels/context_flashattention_nopad.py
dlblas/kernels/cross_entropy.py
dlblas/kernels/decode_attention.py
dlblas/kernels/element_mul.py
dlblas/kernels/extend_attention.py
dlblas/kernels/ffn.py
dlblas/kernels/fill_kv_cache.py
dlblas/kernels/flash_attention.py
dlblas/kernels/flash_attention_v2.py
dlblas/kernels/fp8.py
dlblas/kernels/fp8_gemm.py
dlblas/kernels/fused_linear_cross_entropy.py
dlblas/kernels/fused_lora.py
dlblas/kernels/fused_moe.py
dlblas/kernels/fused_moe_v2.py
dlblas/kernels/fused_moe_v3.py
dlblas/kernels/fused_rotary_and_fa.py
dlblas/kernels/fused_rotary_emb.py
dlblas/kernels/grouped_gemm.py
dlblas/kernels/grpo_loss.py
dlblas/kernels/layernorm_gated.py
dlblas/kernels/matmul.py
dlblas/kernels/mbgmm.py
dlblas/kernels/mbgmv.py
dlblas/kernels/moe.py
dlblas/kernels/moe_align_block_size.py
dlblas/kernels/multinomial_sampling.py
dlblas/kernels/paged_attention.py
dlblas/kernels/partial_rotary_emb.py
dlblas/kernels/persistent_matmul.py
dlblas/kernels/prefill_attention.py
dlblas/kernels/quant_dequant.py
dlblas/kernels/rearange_all_gather.py
dlblas/kernels/rms_norm.py
dlblas/kernels/selective_scan.py
dlblas/kernels/selective_state_update.py
dlblas/kernels/topk_gating.py
dlblas/kernels/topk_gating_bwd.py
dlblas/kernels/topk_gating_fwd_part1.py
dlblas/kernels/topk_gating_fwd_part2.py
dlblas/kernels/topk_gating_fwd_part2_position.py
dlblas-0.0.5.dist-info/LICENSE
dlblas-0.0.5.dist-info/METADATA
dlblas-0.0.5.dist-info/WHEEL
dlblas-0.0.5.dist-info/top_level.txt
dlblas-0.0.5.dist-info/RECORD
