Metadata-Version: 2.2
Name: dlblas
Version: 0.0.5
Summary: dlblas
Author: dlblas Team
License: BSD 3-Clause License
Project-URL: Homepage, https://github.com/DeepLink-org/dlBLAS
Classifier: Programming Language :: Python :: 3
Classifier: License :: OSI Approved :: Apache Software License
Classifier: Intended Audience :: Developers
Classifier: Intended Audience :: Information Technology
Classifier: Intended Audience :: Science/Research
Classifier: Topic :: Scientific/Engineering :: Artificial Intelligence
Classifier: Topic :: Scientific/Engineering :: Information Analysis
Requires-Python: >=3.10
License-File: LICENSE
